ImmunoMatch/__init__.py
ImmunoMatch/run_immunomatch.py
immunomatch-0.1.5.dist-info/licenses/LICENSE
immunomatch-0.1.5.dist-info/METADATA
immunomatch-0.1.5.dist-info/WHEEL
immunomatch-0.1.5.dist-info/top_level.txt
immunomatch-0.1.5.dist-info/RECORD
