Metadata-Version: 2.4
Name: ImmunoMatch
Version: 0.1.5
Summary: ImmunoMatch predicts the pairing between heavy and light chains in antibody.
Author-email: Dongjun Guo <d.guo@ucl.ac.uk>, "Deborah K. Dunn-Walters" <d.dunn-walters@surrey.ac.uk>, Franca Fraternali <f.fraternali@ucl.ac.uk>, "Joseph C. F. Ng" <joseph.ng@ucl.ac.uk>
License: MIT
Project-URL: Homepage, https://github.com/Fraternalilab/ImmunoMatch
Requires-Python: >=3.11
License-File: LICENSE
Requires-Dist: numpy
Requires-Dist: pandas
Requires-Dist: transformers
Requires-Dist: rjieba
Requires-Dist: torch
Requires-Dist: datasets
Requires-Dist: scikit-learn
Dynamic: license-file
